<?xml version="1.0" encoding="UTF-8" ?>
<!DOCTYPE mapper PUBLIC "-//mybatis.org//DTD Mapper 3.0//EN" "http://mybatis.org/dtd/mybatis-3-mapper.dtd" >
<mapper namespace="com.haozi.demo.springboot.dao.AquaticSettleSuccessInfoMapper" >
  <resultMap id="BaseResultMap" type="com.haozi.demo.springboot.bean.po.AquaticSettleSuccessInfo" >
    <!--
      WARNING - @mbggenerated
      This element is automatically generated by MyBatis Generator, do not modify.
    -->
    <id column="settle_key" property="settleKey" jdbcType="VARCHAR" />
    <result column="ID" property="id" jdbcType="INTEGER" />
    <result column="SHOP_KEY" property="shopKey" jdbcType="VARCHAR" />
    <result column="settle_time" property="settleTime" jdbcType="TIMESTAMP" />
    <result column="settle_money" property="settleMoney" jdbcType="DECIMAL" />
    <result column="card_no" property="cardNo" jdbcType="VARCHAR" />
    <result column="sms_code" property="smsCode" jdbcType="VARCHAR" />
    <result column="card_key" property="cardKey" jdbcType="VARCHAR" />
    <result column="apply_time" property="applyTime" jdbcType="TIMESTAMP" />
    <result column="platSeq" property="platseq" jdbcType="VARCHAR" />
    <result column="audit_man" property="auditMan" jdbcType="VARCHAR" />
    <result column="audit_time" property="auditTime" jdbcType="TIMESTAMP" />
    <result column="audit_remark" property="auditRemark" jdbcType="VARCHAR" />
    <result column="settle_channel" property="settleChannel" jdbcType="VARCHAR" />
  </resultMap>
  <sql id="Base_Column_List" >
    <!--
      WARNING - @mbggenerated
      This element is automatically generated by MyBatis Generator, do not modify.
    -->
    settle_key, ID, SHOP_KEY, settle_time, settle_money, card_no, sms_code, card_key, 
    apply_time, platSeq, audit_man, audit_time, audit_remark, settle_channel
  </sql>
  <select id="selectByPrimaryKey" resultMap="BaseResultMap" parameterType="java.lang.String" >
    <!--
      WARNING - @mbggenerated
      This element is automatically generated by MyBatis Generator, do not modify.
    -->
    select 
    <include refid="Base_Column_List" />
    from aquatic_settle_success_info
    where settle_key = #{settleKey,jdbcType=VARCHAR}
  </select>
  <delete id="deleteByPrimaryKey" parameterType="java.lang.String" >
    <!--
      WARNING - @mbggenerated
      This element is automatically generated by MyBatis Generator, do not modify.
    -->
    delete from aquatic_settle_success_info
    where settle_key = #{settleKey,jdbcType=VARCHAR}
  </delete>
  <insert id="insert" parameterType="com.haozi.demo.springboot.bean.po.AquaticSettleSuccessInfo" >
    <!--
      WARNING - @mbggenerated
      This element is automatically generated by MyBatis Generator, do not modify.
    -->
    insert into aquatic_settle_success_info (settle_key, ID, SHOP_KEY, 
      settle_time, settle_money, card_no, 
      sms_code, card_key, apply_time, 
      platSeq, audit_man, audit_time, 
      audit_remark, settle_channel)
    values (#{settleKey,jdbcType=VARCHAR}, #{id,jdbcType=INTEGER}, #{shopKey,jdbcType=VARCHAR}, 
      #{settleTime,jdbcType=TIMESTAMP}, #{settleMoney,jdbcType=DECIMAL}, #{cardNo,jdbcType=VARCHAR}, 
      #{smsCode,jdbcType=VARCHAR}, #{cardKey,jdbcType=VARCHAR}, #{applyTime,jdbcType=TIMESTAMP}, 
      #{platseq,jdbcType=VARCHAR}, #{auditMan,jdbcType=VARCHAR}, #{auditTime,jdbcType=TIMESTAMP}, 
      #{auditRemark,jdbcType=VARCHAR}, #{settleChannel,jdbcType=VARCHAR})
  </insert>
  <insert id="insertSelective" parameterType="com.haozi.demo.springboot.bean.po.AquaticSettleSuccessInfo" >
    <!--
      WARNING - @mbggenerated
      This element is automatically generated by MyBatis Generator, do not modify.
    -->
    insert into aquatic_settle_success_info
    <trim prefix="(" suffix=")" suffixOverrides="," >
      <if test="settleKey != null" >
        settle_key,
      </if>
      <if test="id != null" >
        ID,
      </if>
      <if test="shopKey != null" >
        SHOP_KEY,
      </if>
      <if test="settleTime != null" >
        settle_time,
      </if>
      <if test="settleMoney != null" >
        settle_money,
      </if>
      <if test="cardNo != null" >
        card_no,
      </if>
      <if test="smsCode != null" >
        sms_code,
      </if>
      <if test="cardKey != null" >
        card_key,
      </if>
      <if test="applyTime != null" >
        apply_time,
      </if>
      <if test="platseq != null" >
        platSeq,
      </if>
      <if test="auditMan != null" >
        audit_man,
      </if>
      <if test="auditTime != null" >
        audit_time,
      </if>
      <if test="auditRemark != null" >
        audit_remark,
      </if>
      <if test="settleChannel != null" >
        settle_channel,
      </if>
    </trim>
    <trim prefix="values (" suffix=")" suffixOverrides="," >
      <if test="settleKey != null" >
        #{settleKey,jdbcType=VARCHAR},
      </if>
      <if test="id != null" >
        #{id,jdbcType=INTEGER},
      </if>
      <if test="shopKey != null" >
        #{shopKey,jdbcType=VARCHAR},
      </if>
      <if test="settleTime != null" >
        #{settleTime,jdbcType=TIMESTAMP},
      </if>
      <if test="settleMoney != null" >
        #{settleMoney,jdbcType=DECIMAL},
      </if>
      <if test="cardNo != null" >
        #{cardNo,jdbcType=VARCHAR},
      </if>
      <if test="smsCode != null" >
        #{smsCode,jdbcType=VARCHAR},
      </if>
      <if test="cardKey != null" >
        #{cardKey,jdbcType=VARCHAR},
      </if>
      <if test="applyTime != null" >
        #{applyTime,jdbcType=TIMESTAMP},
      </if>
      <if test="platseq != null" >
        #{platseq,jdbcType=VARCHAR},
      </if>
      <if test="auditMan != null" >
        #{auditMan,jdbcType=VARCHAR},
      </if>
      <if test="auditTime != null" >
        #{auditTime,jdbcType=TIMESTAMP},
      </if>
      <if test="auditRemark != null" >
        #{auditRemark,jdbcType=VARCHAR},
      </if>
      <if test="settleChannel != null" >
        #{settleChannel,jdbcType=VARCHAR},
      </if>
    </trim>
  </insert>
  <update id="updateByPrimaryKeySelective" parameterType="com.haozi.demo.springboot.bean.po.AquaticSettleSuccessInfo" >
    <!--
      WARNING - @mbggenerated
      This element is automatically generated by MyBatis Generator, do not modify.
    -->
    update aquatic_settle_success_info
    <set >
      <if test="id != null" >
        ID = #{id,jdbcType=INTEGER},
      </if>
      <if test="shopKey != null" >
        SHOP_KEY = #{shopKey,jdbcType=VARCHAR},
      </if>
      <if test="settleTime != null" >
        settle_time = #{settleTime,jdbcType=TIMESTAMP},
      </if>
      <if test="settleMoney != null" >
        settle_money = #{settleMoney,jdbcType=DECIMAL},
      </if>
      <if test="cardNo != null" >
        card_no = #{cardNo,jdbcType=VARCHAR},
      </if>
      <if test="smsCode != null" >
        sms_code = #{smsCode,jdbcType=VARCHAR},
      </if>
      <if test="cardKey != null" >
        card_key = #{cardKey,jdbcType=VARCHAR},
      </if>
      <if test="applyTime != null" >
        apply_time = #{applyTime,jdbcType=TIMESTAMP},
      </if>
      <if test="platseq != null" >
        platSeq = #{platseq,jdbcType=VARCHAR},
      </if>
      <if test="auditMan != null" >
        audit_man = #{auditMan,jdbcType=VARCHAR},
      </if>
      <if test="auditTime != null" >
        audit_time = #{auditTime,jdbcType=TIMESTAMP},
      </if>
      <if test="auditRemark != null" >
        audit_remark = #{auditRemark,jdbcType=VARCHAR},
      </if>
      <if test="settleChannel != null" >
        settle_channel = #{settleChannel,jdbcType=VARCHAR},
      </if>
    </set>
    where settle_key = #{settleKey,jdbcType=VARCHAR}
  </update>
  <update id="updateByPrimaryKey" parameterType="com.haozi.demo.springboot.bean.po.AquaticSettleSuccessInfo" >
    <!--
      WARNING - @mbggenerated
      This element is automatically generated by MyBatis Generator, do not modify.
    -->
    update aquatic_settle_success_info
    set ID = #{id,jdbcType=INTEGER},
      SHOP_KEY = #{shopKey,jdbcType=VARCHAR},
      settle_time = #{settleTime,jdbcType=TIMESTAMP},
      settle_money = #{settleMoney,jdbcType=DECIMAL},
      card_no = #{cardNo,jdbcType=VARCHAR},
      sms_code = #{smsCode,jdbcType=VARCHAR},
      card_key = #{cardKey,jdbcType=VARCHAR},
      apply_time = #{applyTime,jdbcType=TIMESTAMP},
      platSeq = #{platseq,jdbcType=VARCHAR},
      audit_man = #{auditMan,jdbcType=VARCHAR},
      audit_time = #{auditTime,jdbcType=TIMESTAMP},
      audit_remark = #{auditRemark,jdbcType=VARCHAR},
      settle_channel = #{settleChannel,jdbcType=VARCHAR}
    where settle_key = #{settleKey,jdbcType=VARCHAR}
  </update>
</mapper>